{
  "movies": ["60757c00291ccb5f16ab248e"],
  "_id": "60757890291ccb5f16ab2487",
  "name": "Michael J. Fox",
  "bio": "Michael Andrew Fox, known professionally as Michael J. Fox, is a Canadian-American retired actor, author, film producer, and activist. Beginning his career in the 1970s, he first rose to prominence for portraying Alex P. Keaton on the NBC sitcom Family Ties (1982–1989). Fox achieved further recognition as protagonist Marty McFly in the Back to the Future film trilogy (1985–1990).",
  "birthYear": 1961
}
